{"cameraMode":{"drawMode":0,"name":"Shaded","section":"Shading Mode"},"sceneLighting":true,"audioPlay":false,"sceneViewState":{"m_AlwaysRefresh":false,"showFog":true,"showSkybox":true,"showFlares":true,"showImageEffects":true,"showParticleSystems":true,"showVisualEffectGraphs":true,"m_FxEnabled":true},"in2DMode":false,"pivot":{"x":-4.6112470626831059,"y":-5.524425506591797,"z":1.9105525016784669},"rotation":{"x":0.31474119424819949,"y":-0.41119667887687685,"z":0.15381120145320893,"w":0.8415687680244446},"size":7.913763999938965,"orthographic":false}